{
  "deployment": {
    "status": "ready",
    "environment": "production",
    "timestamp": "2025-11-17T03:20:35.703Z",
    "version": "1.0.0",
    "cloudflare": {
      "zoneId": "b549a7b1e320833b31d01f7b702f054d",
      "accountId": "548a933e3812ca9cd840b787ca7e1eb1"
    }
  },
  "build": {
    "totalFiles": 8,
    "criticalFiles": 6,
    "buildSize": 66106,
    "optimization": "production-ready"
  },
  "performance": {
    "targets": {
      "targetLCP": 2000,
      "targetCLS": 0.05,
      "targetINP": 150,
      "targetFCP": 1200
    },
    "expectedImprovements": "45-70% Core Web Vitals improvement",
    "monitoring": "real-time"
  },
  "features": [
    "Real-time performance monitoring",
    "Production-optimized HTML/CSS",
    "Cloudflare CDN integration",
    "SEO-friendly sitemap",
    "Security headers",
    "API endpoints for metrics"
  ],
  "status": {
    "build": "✅ Complete",
    "optimization": "✅ Complete",
    "deployment": "✅ Ready for Cloudflare Pages"
  }
}